{
  "year": 2006,
  "fetched_at": "2026-06-16T11:45:42Z",
  "count": 64,
  "matches": [
    {
      "id": null,
      "date": "2006-06-09T00:00:00Z",
      "status": "FINISHED",
      "matchday": 1,
      "stage": "GROUP_STAGE",
      "group": "Group A",
      "home_team_id": 686765747,
      "home_team_name": "Germany",
      "away_team_id": 1565394076,
      "away_team_name": "Costa Rica",
      "home_goals": 4,
      "away_goals": 2,
      "result": "H",
      "source": "openfootball"
    },
    {
      "id": null,
      "date": "2006-06-09T00:00:00Z",
      "status": "FINISHED",
      "matchday": 1,
      "stage": "GROUP_STAGE",
      "group": "Group A",
      "home_team_id": 1862845917,
      "home_team_name": "Poland",
      "away_team_id": 726276149,
      "away_team_name": "Ecuador",
      "home_goals": 0,
      "away_goals": 2,
      "result": "A",
      "source": "openfootball"
    },
    {
      "id": null,
      "date": "2006-06-14T00:00:00Z",
      "status": "FINISHED",
      "matchday": 6,
      "stage": "GROUP_STAGE",
      "group": "Group A",
      "home_team_id": 686765747,
      "home_team_name": "Germany",
      "away_team_id": 1862845917,
      "away_team_name": "Poland",
      "home_goals": 1,
      "away_goals": 0,
      "result": "H",
      "source": "openfootball"
    },
    {
      "id": null,
      "date": "2006-06-15T00:00:00Z",
      "status": "FINISHED",
      "matchday": 7,
      "stage": "GROUP_STAGE",
      "group": "Group A",
      "home_team_id": 726276149,
      "home_team_name": "Ecuador",
      "away_team_id": 1565394076,
      "away_team_name": "Costa Rica",
      "home_goals": 3,
      "away_goals": 0,
      "result": "H",
      "source": "openfootball"
    },
    {
      "id": null,
      "date": "2006-06-20T00:00:00Z",
      "status": "FINISHED",
      "matchday": 12,
      "stage": "GROUP_STAGE",
      "group": "Group A",
      "home_team_id": 726276149,
      "home_team_name": "Ecuador",
      "away_team_id": 686765747,
      "away_team_name": "Germany",
      "home_goals": 0,
      "away_goals": 3,
      "result": "A",
      "source": "openfootball"
    },
    {
      "id": null,
      "date": "2006-06-20T00:00:00Z",
      "status": "FINISHED",
      "matchday": 12,
      "stage": "GROUP_STAGE",
      "group": "Group A",
      "home_team_id": 1565394076,
      "home_team_name": "Costa Rica",
      "away_team_id": 1862845917,
      "away_team_name": "Poland",
      "home_goals": 1,
      "away_goals": 2,
      "result": "A",
      "source": "openfootball"
    },
    {
      "id": null,
      "date": "2006-06-10T00:00:00Z",
      "status": "FINISHED",
      "matchday": 2,
      "stage": "GROUP_STAGE",
      "group": "Group B",
      "home_team_id": 4102578634,
      "home_team_name": "England",
      "away_team_id": 1001373656,
      "away_team_name": "Paraguay",
      "home_goals": 1,
      "away_goals": 0,
      "result": "H",
      "source": "openfootball"
    },
    {
      "id": null,
      "date": "2006-06-10T00:00:00Z",
      "status": "FINISHED",
      "matchday": 2,
      "stage": "GROUP_STAGE",
      "group": "Group B",
      "home_team_id": 156550384,
      "home_team_name": "Trinidad and Tobago",
      "away_team_id": 2296721124,
      "away_team_name": "Sweden",
      "home_goals": 0,
      "away_goals": 0,
      "result": "D",
      "source": "openfootball"
    },
    {
      "id": null,
      "date": "2006-06-15T00:00:00Z",
      "status": "FINISHED",
      "matchday": 7,
      "stage": "GROUP_STAGE",
      "group": "Group B",
      "home_team_id": 4102578634,
      "home_team_name": "England",
      "away_team_id": 156550384,
      "away_team_name": "Trinidad and Tobago",
      "home_goals": 2,
      "away_goals": 0,
      "result": "H",
      "source": "openfootball"
    },
    {
      "id": null,
      "date": "2006-06-15T00:00:00Z",
      "status": "FINISHED",
      "matchday": 7,
      "stage": "GROUP_STAGE",
      "group": "Group B",
      "home_team_id": 2296721124,
      "home_team_name": "Sweden",
      "away_team_id": 1001373656,
      "away_team_name": "Paraguay",
      "home_goals": 1,
      "away_goals": 0,
      "result": "H",
      "source": "openfootball"
    },
    {
      "id": null,
      "date": "2006-06-20T00:00:00Z",
      "status": "FINISHED",
      "matchday": 12,
      "stage": "GROUP_STAGE",
      "group": "Group B",
      "home_team_id": 2296721124,
      "home_team_name": "Sweden",
      "away_team_id": 4102578634,
      "away_team_name": "England",
      "home_goals": 2,
      "away_goals": 2,
      "result": "D",
      "source": "openfootball"
    },
    {
      "id": null,
      "date": "2006-06-20T00:00:00Z",
      "status": "FINISHED",
      "matchday": 12,
      "stage": "GROUP_STAGE",
      "group": "Group B",
      "home_team_id": 1001373656,
      "home_team_name": "Paraguay",
      "away_team_id": 156550384,
      "away_team_name": "Trinidad and Tobago",
      "home_goals": 2,
      "away_goals": 0,
      "result": "H",
      "source": "openfootball"
    },
    {
      "id": null,
      "date": "2006-06-10T00:00:00Z",
      "status": "FINISHED",
      "matchday": 2,
      "stage": "GROUP_STAGE",
      "group": "Group C",
      "home_team_id": 710061511,
      "home_team_name": "Argentina",
      "away_team_id": 3293236182,
      "away_team_name": "C\u00f4te d'Ivoire",
      "home_goals": 2,
      "away_goals": 1,
      "result": "H",
      "source": "openfootball"
    },
    {
      "id": null,
      "date": "2006-06-11T00:00:00Z",
      "status": "FINISHED",
      "matchday": 3,
      "stage": "GROUP_STAGE",
      "group": "Group C",
      "home_team_id": 1532110640,
      "home_team_name": "Serbia and Montenegro",
      "away_team_id": 1629702244,
      "away_team_name": "Netherlands",
      "home_goals": 0,
      "away_goals": 1,
      "result": "A",
      "source": "openfootball"
    },
    {
      "id": null,
      "date": "2006-06-16T00:00:00Z",
      "status": "FINISHED",
      "matchday": 8,
      "stage": "GROUP_STAGE",
      "group": "Group C",
      "home_team_id": 710061511,
      "home_team_name": "Argentina",
      "away_team_id": 1532110640,
      "away_team_name": "Serbia and Montenegro",
      "home_goals": 6,
      "away_goals": 0,
      "result": "H",
      "source": "openfootball"
    },
    {
      "id": null,
      "date": "2006-06-16T00:00:00Z",
      "status": "FINISHED",
      "matchday": 8,
      "stage": "GROUP_STAGE",
      "group": "Group C",
      "home_team_id": 1629702244,
      "home_team_name": "Netherlands",
      "away_team_id": 3293236182,
      "away_team_name": "C\u00f4te d'Ivoire",
      "home_goals": 2,
      "away_goals": 1,
      "result": "H",
      "source": "openfootball"
    },
    {
      "id": null,
      "date": "2006-06-21T00:00:00Z",
      "status": "FINISHED",
      "matchday": 13,
      "stage": "GROUP_STAGE",
      "group": "Group C",
      "home_team_id": 1629702244,
      "home_team_name": "Netherlands",
      "away_team_id": 710061511,
      "away_team_name": "Argentina",
      "home_goals": 0,
      "away_goals": 0,
      "result": "D",
      "source": "openfootball"
    },
    {
      "id": null,
      "date": "2006-06-21T00:00:00Z",
      "status": "FINISHED",
      "matchday": 13,
      "stage": "GROUP_STAGE",
      "group": "Group C",
      "home_team_id": 3293236182,
      "home_team_name": "C\u00f4te d'Ivoire",
      "away_team_id": 1532110640,
      "away_team_name": "Serbia and Montenegro",
      "home_goals": 3,
      "away_goals": 2,
      "result": "H",
      "source": "openfootball"
    },
    {
      "id": null,
      "date": "2006-06-11T00:00:00Z",
      "status": "FINISHED",
      "matchday": 3,
      "stage": "GROUP_STAGE",
      "group": "Group D",
      "home_team_id": 1323288868,
      "home_team_name": "Mexico",
      "away_team_id": 1862958422,
      "away_team_name": "Iran",
      "home_goals": 3,
      "away_goals": 1,
      "result": "H",
      "source": "openfootball"
    },
    {
      "id": null,
      "date": "2006-06-11T00:00:00Z",
      "status": "FINISHED",
      "matchday": 3,
      "stage": "GROUP_STAGE",
      "group": "Group D",
      "home_team_id": 3856710979,
      "home_team_name": "Angola",
      "away_team_id": 2920213102,
      "away_team_name": "Portugal",
      "home_goals": 0,
      "away_goals": 1,
      "result": "A",
      "source": "openfootball"
    },
    {
      "id": null,
      "date": "2006-06-16T00:00:00Z",
      "status": "FINISHED",
      "matchday": 8,
      "stage": "GROUP_STAGE",
      "group": "Group D",
      "home_team_id": 1323288868,
      "home_team_name": "Mexico",
      "away_team_id": 3856710979,
      "away_team_name": "Angola",
      "home_goals": 0,
      "away_goals": 0,
      "result": "D",
      "source": "openfootball"
    },
    {
      "id": null,
      "date": "2006-06-17T00:00:00Z",
      "status": "FINISHED",
      "matchday": 9,
      "stage": "GROUP_STAGE",
      "group": "Group D",
      "home_team_id": 2920213102,
      "home_team_name": "Portugal",
      "away_team_id": 1862958422,
      "away_team_name": "Iran",
      "home_goals": 2,
      "away_goals": 0,
      "result": "H",
      "source": "openfootball"
    },
    {
      "id": null,
      "date": "2006-06-21T00:00:00Z",
      "status": "FINISHED",
      "matchday": 13,
      "stage": "GROUP_STAGE",
      "group": "Group D",
      "home_team_id": 2920213102,
      "home_team_name": "Portugal",
      "away_team_id": 1323288868,
      "away_team_name": "Mexico",
      "home_goals": 2,
      "away_goals": 1,
      "result": "H",
      "source": "openfootball"
    },
    {
      "id": null,
      "date": "2006-06-21T00:00:00Z",
      "status": "FINISHED",
      "matchday": 13,
      "stage": "GROUP_STAGE",
      "group": "Group D",
      "home_team_id": 1862958422,
      "home_team_name": "Iran",
      "away_team_id": 3856710979,
      "away_team_name": "Angola",
      "home_goals": 1,
      "away_goals": 1,
      "result": "D",
      "source": "openfootball"
    },
    {
      "id": null,
      "date": "2006-06-12T00:00:00Z",
      "status": "FINISHED",
      "matchday": 4,
      "stage": "GROUP_STAGE",
      "group": "Group E",
      "home_team_id": 3132402743,
      "home_team_name": "Italy",
      "away_team_id": 241191387,
      "away_team_name": "Ghana",
      "home_goals": 2,
      "away_goals": 0,
      "result": "H",
      "source": "openfootball"
    },
    {
      "id": null,
      "date": "2006-06-12T00:00:00Z",
      "status": "FINISHED",
      "matchday": 4,
      "stage": "GROUP_STAGE",
      "group": "Group E",
      "home_team_id": 2913284868,
      "home_team_name": "USA",
      "away_team_id": 844215516,
      "away_team_name": "Czech Republic",
      "home_goals": 0,
      "away_goals": 3,
      "result": "A",
      "source": "openfootball"
    },
    {
      "id": null,
      "date": "2006-06-17T00:00:00Z",
      "status": "FINISHED",
      "matchday": 9,
      "stage": "GROUP_STAGE",
      "group": "Group E",
      "home_team_id": 3132402743,
      "home_team_name": "Italy",
      "away_team_id": 2913284868,
      "away_team_name": "USA",
      "home_goals": 1,
      "away_goals": 1,
      "result": "D",
      "source": "openfootball"
    },
    {
      "id": null,
      "date": "2006-06-17T00:00:00Z",
      "status": "FINISHED",
      "matchday": 9,
      "stage": "GROUP_STAGE",
      "group": "Group E",
      "home_team_id": 844215516,
      "home_team_name": "Czech Republic",
      "away_team_id": 241191387,
      "away_team_name": "Ghana",
      "home_goals": 0,
      "away_goals": 2,
      "result": "A",
      "source": "openfootball"
    },
    {
      "id": null,
      "date": "2006-06-22T00:00:00Z",
      "status": "FINISHED",
      "matchday": 14,
      "stage": "GROUP_STAGE",
      "group": "Group E",
      "home_team_id": 844215516,
      "home_team_name": "Czech Republic",
      "away_team_id": 3132402743,
      "away_team_name": "Italy",
      "home_goals": 0,
      "away_goals": 2,
      "result": "A",
      "source": "openfootball"
    },
    {
      "id": null,
      "date": "2006-06-22T00:00:00Z",
      "status": "FINISHED",
      "matchday": 14,
      "stage": "GROUP_STAGE",
      "group": "Group E",
      "home_team_id": 241191387,
      "home_team_name": "Ghana",
      "away_team_id": 2913284868,
      "away_team_name": "USA",
      "home_goals": 2,
      "away_goals": 1,
      "result": "H",
      "source": "openfootball"
    },
    {
      "id": null,
      "date": "2006-06-13T00:00:00Z",
      "status": "FINISHED",
      "matchday": 5,
      "stage": "GROUP_STAGE",
      "group": "Group F",
      "home_team_id": 1851761881,
      "home_team_name": "Brazil",
      "away_team_id": 645283928,
      "away_team_name": "Croatia",
      "home_goals": 1,
      "away_goals": 0,
      "result": "H",
      "source": "openfootball"
    },
    {
      "id": null,
      "date": "2006-06-12T00:00:00Z",
      "status": "FINISHED",
      "matchday": 4,
      "stage": "GROUP_STAGE",
      "group": "Group F",
      "home_team_id": 4213855446,
      "home_team_name": "Australia",
      "away_team_id": 1468978596,
      "away_team_name": "Japan",
      "home_goals": 3,
      "away_goals": 1,
      "result": "H",
      "source": "openfootball"
    },
    {
      "id": null,
      "date": "2006-06-18T00:00:00Z",
      "status": "FINISHED",
      "matchday": 10,
      "stage": "GROUP_STAGE",
      "group": "Group F",
      "home_team_id": 1851761881,
      "home_team_name": "Brazil",
      "away_team_id": 4213855446,
      "away_team_name": "Australia",
      "home_goals": 2,
      "away_goals": 0,
      "result": "H",
      "source": "openfootball"
    },
    {
      "id": null,
      "date": "2006-06-18T00:00:00Z",
      "status": "FINISHED",
      "matchday": 10,
      "stage": "GROUP_STAGE",
      "group": "Group F",
      "home_team_id": 1468978596,
      "home_team_name": "Japan",
      "away_team_id": 645283928,
      "away_team_name": "Croatia",
      "home_goals": 0,
      "away_goals": 0,
      "result": "D",
      "source": "openfootball"
    },
    {
      "id": null,
      "date": "2006-06-22T00:00:00Z",
      "status": "FINISHED",
      "matchday": 14,
      "stage": "GROUP_STAGE",
      "group": "Group F",
      "home_team_id": 1468978596,
      "home_team_name": "Japan",
      "away_team_id": 1851761881,
      "away_team_name": "Brazil",
      "home_goals": 1,
      "away_goals": 4,
      "result": "A",
      "source": "openfootball"
    },
    {
      "id": null,
      "date": "2006-06-22T00:00:00Z",
      "status": "FINISHED",
      "matchday": 14,
      "stage": "GROUP_STAGE",
      "group": "Group F",
      "home_team_id": 645283928,
      "home_team_name": "Croatia",
      "away_team_id": 4213855446,
      "away_team_name": "Australia",
      "home_goals": 2,
      "away_goals": 2,
      "result": "D",
      "source": "openfootball"
    },
    {
      "id": null,
      "date": "2006-06-13T00:00:00Z",
      "status": "FINISHED",
      "matchday": 5,
      "stage": "GROUP_STAGE",
      "group": "Group G",
      "home_team_id": 3781547250,
      "home_team_name": "France",
      "away_team_id": 228349791,
      "away_team_name": "Switzerland",
      "home_goals": 0,
      "away_goals": 0,
      "result": "D",
      "source": "openfootball"
    },
    {
      "id": null,
      "date": "2006-06-13T00:00:00Z",
      "status": "FINISHED",
      "matchday": 5,
      "stage": "GROUP_STAGE",
      "group": "Group G",
      "home_team_id": 2802097683,
      "home_team_name": "South Korea",
      "away_team_id": 3664725787,
      "away_team_name": "Togo",
      "home_goals": 2,
      "away_goals": 1,
      "result": "H",
      "source": "openfootball"
    },
    {
      "id": null,
      "date": "2006-06-18T00:00:00Z",
      "status": "FINISHED",
      "matchday": 10,
      "stage": "GROUP_STAGE",
      "group": "Group G",
      "home_team_id": 3781547250,
      "home_team_name": "France",
      "away_team_id": 2802097683,
      "away_team_name": "South Korea",
      "home_goals": 1,
      "away_goals": 1,
      "result": "D",
      "source": "openfootball"
    },
    {
      "id": null,
      "date": "2006-06-19T00:00:00Z",
      "status": "FINISHED",
      "matchday": 11,
      "stage": "GROUP_STAGE",
      "group": "Group G",
      "home_team_id": 3664725787,
      "home_team_name": "Togo",
      "away_team_id": 228349791,
      "away_team_name": "Switzerland",
      "home_goals": 0,
      "away_goals": 2,
      "result": "A",
      "source": "openfootball"
    },
    {
      "id": null,
      "date": "2006-06-23T00:00:00Z",
      "status": "FINISHED",
      "matchday": 15,
      "stage": "GROUP_STAGE",
      "group": "Group G",
      "home_team_id": 3664725787,
      "home_team_name": "Togo",
      "away_team_id": 3781547250,
      "away_team_name": "France",
      "home_goals": 0,
      "away_goals": 2,
      "result": "A",
      "source": "openfootball"
    },
    {
      "id": null,
      "date": "2006-06-23T00:00:00Z",
      "status": "FINISHED",
      "matchday": 15,
      "stage": "GROUP_STAGE",
      "group": "Group G",
      "home_team_id": 228349791,
      "home_team_name": "Switzerland",
      "away_team_id": 2802097683,
      "away_team_name": "South Korea",
      "home_goals": 2,
      "away_goals": 0,
      "result": "H",
      "source": "openfootball"
    },
    {
      "id": null,
      "date": "2006-06-14T00:00:00Z",
      "status": "FINISHED",
      "matchday": 6,
      "stage": "GROUP_STAGE",
      "group": "Group H",
      "home_team_id": 390583474,
      "home_team_name": "Spain",
      "away_team_id": 1259279705,
      "away_team_name": "Ukraine",
      "home_goals": 4,
      "away_goals": 0,
      "result": "H",
      "source": "openfootball"
    },
    {
      "id": null,
      "date": "2006-06-14T00:00:00Z",
      "status": "FINISHED",
      "matchday": 6,
      "stage": "GROUP_STAGE",
      "group": "Group H",
      "home_team_id": 1795685710,
      "home_team_name": "Tunisia",
      "away_team_id": 56972996,
      "away_team_name": "Saudi Arabia",
      "home_goals": 2,
      "away_goals": 2,
      "result": "D",
      "source": "openfootball"
    },
    {
      "id": null,
      "date": "2006-06-19T00:00:00Z",
      "status": "FINISHED",
      "matchday": 11,
      "stage": "GROUP_STAGE",
      "group": "Group H",
      "home_team_id": 390583474,
      "home_team_name": "Spain",
      "away_team_id": 1795685710,
      "away_team_name": "Tunisia",
      "home_goals": 3,
      "away_goals": 1,
      "result": "H",
      "source": "openfootball"
    },
    {
      "id": null,
      "date": "2006-06-19T00:00:00Z",
      "status": "FINISHED",
      "matchday": 11,
      "stage": "GROUP_STAGE",
      "group": "Group H",
      "home_team_id": 56972996,
      "home_team_name": "Saudi Arabia",
      "away_team_id": 1259279705,
      "away_team_name": "Ukraine",
      "home_goals": 0,
      "away_goals": 4,
      "result": "A",
      "source": "openfootball"
    },
    {
      "id": null,
      "date": "2006-06-23T00:00:00Z",
      "status": "FINISHED",
      "matchday": 15,
      "stage": "GROUP_STAGE",
      "group": "Group H",
      "home_team_id": 56972996,
      "home_team_name": "Saudi Arabia",
      "away_team_id": 390583474,
      "away_team_name": "Spain",
      "home_goals": 0,
      "away_goals": 1,
      "result": "A",
      "source": "openfootball"
    },
    {
      "id": null,
      "date": "2006-06-23T00:00:00Z",
      "status": "FINISHED",
      "matchday": 15,
      "stage": "GROUP_STAGE",
      "group": "Group H",
      "home_team_id": 1259279705,
      "home_team_name": "Ukraine",
      "away_team_id": 1795685710,
      "away_team_name": "Tunisia",
      "home_goals": 1,
      "away_goals": 0,
      "result": "H",
      "source": "openfootball"
    },
    {
      "id": null,
      "date": "2006-06-24T00:00:00Z",
      "status": "FINISHED",
      "matchday": null,
      "stage": "LAST_16",
      "group": null,
      "home_team_id": 686765747,
      "home_team_name": "Germany",
      "away_team_id": 2296721124,
      "away_team_name": "Sweden",
      "home_goals": 2,
      "away_goals": 0,
      "result": "H",
      "source": "openfootball"
    },
    {
      "id": null,
      "date": "2006-06-24T00:00:00Z",
      "status": "FINISHED",
      "matchday": null,
      "stage": "LAST_16",
      "group": null,
      "home_team_id": 710061511,
      "home_team_name": "Argentina",
      "away_team_id": 1323288868,
      "away_team_name": "Mexico",
      "home_goals": 1,
      "away_goals": 1,
      "result": "D",
      "source": "openfootball"
    },
    {
      "id": null,
      "date": "2006-06-25T00:00:00Z",
      "status": "FINISHED",
      "matchday": null,
      "stage": "LAST_16",
      "group": null,
      "home_team_id": 4102578634,
      "home_team_name": "England",
      "away_team_id": 726276149,
      "away_team_name": "Ecuador",
      "home_goals": 1,
      "away_goals": 0,
      "result": "H",
      "source": "openfootball"
    },
    {
      "id": null,
      "date": "2006-06-25T00:00:00Z",
      "status": "FINISHED",
      "matchday": null,
      "stage": "LAST_16",
      "group": null,
      "home_team_id": 2920213102,
      "home_team_name": "Portugal",
      "away_team_id": 1629702244,
      "away_team_name": "Netherlands",
      "home_goals": 1,
      "away_goals": 0,
      "result": "H",
      "source": "openfootball"
    },
    {
      "id": null,
      "date": "2006-06-26T00:00:00Z",
      "status": "FINISHED",
      "matchday": null,
      "stage": "LAST_16",
      "group": null,
      "home_team_id": 3132402743,
      "home_team_name": "Italy",
      "away_team_id": 4213855446,
      "away_team_name": "Australia",
      "home_goals": 1,
      "away_goals": 0,
      "result": "H",
      "source": "openfootball"
    },
    {
      "id": null,
      "date": "2006-06-26T00:00:00Z",
      "status": "FINISHED",
      "matchday": null,
      "stage": "LAST_16",
      "group": null,
      "home_team_id": 228349791,
      "home_team_name": "Switzerland",
      "away_team_id": 1259279705,
      "away_team_name": "Ukraine",
      "home_goals": 0,
      "away_goals": 0,
      "result": "D",
      "source": "openfootball"
    },
    {
      "id": null,
      "date": "2006-06-27T00:00:00Z",
      "status": "FINISHED",
      "matchday": null,
      "stage": "LAST_16",
      "group": null,
      "home_team_id": 1851761881,
      "home_team_name": "Brazil",
      "away_team_id": 241191387,
      "away_team_name": "Ghana",
      "home_goals": 3,
      "away_goals": 0,
      "result": "H",
      "source": "openfootball"
    },
    {
      "id": null,
      "date": "2006-06-27T00:00:00Z",
      "status": "FINISHED",
      "matchday": null,
      "stage": "LAST_16",
      "group": null,
      "home_team_id": 390583474,
      "home_team_name": "Spain",
      "away_team_id": 3781547250,
      "away_team_name": "France",
      "home_goals": 1,
      "away_goals": 3,
      "result": "A",
      "source": "openfootball"
    },
    {
      "id": null,
      "date": "2006-06-30T00:00:00Z",
      "status": "FINISHED",
      "matchday": null,
      "stage": "QUARTER_FINALS",
      "group": null,
      "home_team_id": 686765747,
      "home_team_name": "Germany",
      "away_team_id": 710061511,
      "away_team_name": "Argentina",
      "home_goals": 1,
      "away_goals": 1,
      "result": "D",
      "source": "openfootball"
    },
    {
      "id": null,
      "date": "2006-06-30T00:00:00Z",
      "status": "FINISHED",
      "matchday": null,
      "stage": "QUARTER_FINALS",
      "group": null,
      "home_team_id": 3132402743,
      "home_team_name": "Italy",
      "away_team_id": 1259279705,
      "away_team_name": "Ukraine",
      "home_goals": 3,
      "away_goals": 0,
      "result": "H",
      "source": "openfootball"
    },
    {
      "id": null,
      "date": "2006-07-01T00:00:00Z",
      "status": "FINISHED",
      "matchday": null,
      "stage": "QUARTER_FINALS",
      "group": null,
      "home_team_id": 4102578634,
      "home_team_name": "England",
      "away_team_id": 2920213102,
      "away_team_name": "Portugal",
      "home_goals": 0,
      "away_goals": 0,
      "result": "D",
      "source": "openfootball"
    },
    {
      "id": null,
      "date": "2006-07-01T00:00:00Z",
      "status": "FINISHED",
      "matchday": null,
      "stage": "QUARTER_FINALS",
      "group": null,
      "home_team_id": 1851761881,
      "home_team_name": "Brazil",
      "away_team_id": 3781547250,
      "away_team_name": "France",
      "home_goals": 0,
      "away_goals": 1,
      "result": "A",
      "source": "openfootball"
    },
    {
      "id": null,
      "date": "2006-07-04T00:00:00Z",
      "status": "FINISHED",
      "matchday": null,
      "stage": "SEMI_FINALS",
      "group": null,
      "home_team_id": 686765747,
      "home_team_name": "Germany",
      "away_team_id": 3132402743,
      "away_team_name": "Italy",
      "home_goals": 0,
      "away_goals": 0,
      "result": "D",
      "source": "openfootball"
    },
    {
      "id": null,
      "date": "2006-07-05T00:00:00Z",
      "status": "FINISHED",
      "matchday": null,
      "stage": "SEMI_FINALS",
      "group": null,
      "home_team_id": 2920213102,
      "home_team_name": "Portugal",
      "away_team_id": 3781547250,
      "away_team_name": "France",
      "home_goals": 0,
      "away_goals": 1,
      "result": "A",
      "source": "openfootball"
    },
    {
      "id": null,
      "date": "2006-07-08T00:00:00Z",
      "status": "FINISHED",
      "matchday": null,
      "stage": "THIRD-PLACE PLAY-OFF",
      "group": null,
      "home_team_id": 686765747,
      "home_team_name": "Germany",
      "away_team_id": 2920213102,
      "away_team_name": "Portugal",
      "home_goals": 3,
      "away_goals": 1,
      "result": "H",
      "source": "openfootball"
    },
    {
      "id": null,
      "date": "2006-07-09T00:00:00Z",
      "status": "FINISHED",
      "matchday": null,
      "stage": "FINAL",
      "group": null,
      "home_team_id": 3132402743,
      "home_team_name": "Italy",
      "away_team_id": 3781547250,
      "away_team_name": "France",
      "home_goals": 1,
      "away_goals": 1,
      "result": "D",
      "source": "openfootball"
    }
  ]
}